{"name":"Select Refundable flight option","id":"expedia-page;select-refundable-flight-option","userStory":{"id":"expedia-page","storyName":"Expedia Page","path":"SearchFlights.feature","narrative":"  As a web user\n  I want to use Expedia page\n  to look for a flight according to my needs","type":"feature"},"featureTag":{"name":"Expedia Page","type":"feature"},"title":"Select Refundable flight option","tags":[{"name":"Expedia page","type":"feature"}],"startTime":"2020-10-11T21:03:37.874-05:00[America/Bogota]","duration":12,"projectKey":"","manual":false,"testSource":"Cucumber","result":"SUCCESS"}